{
    "anims": [
        {
            "key": "loadAnimation",
            "type": "frame",
            "frames": [
                {
                    "key": "loading_win-sheet0",
                    "frame": 0,
                    "duration": 0,
                    "keyframe": false
                },
                {
                    "key": "loading_win-sheet0",
                    "frame": 1,
                    "duration": 0,
                    "keyframe": false
                },
                {
                    "key": "loading_win-sheet0",
                    "frame": 2,
                    "duration": 0,
                    "keyframe": false
                },
                {
                    "key": "loading_win-sheet0",
                    "frame": 3,
                    "duration": 0,
                    "keyframe": false
                }
            ],
            "frameRate": 8,
            "skipMissedFrames": true,
            "repeat": -1
        }
    ],
    "globalTimeScale": 1,
    "meta": {
        "app": "Phaser Editor 2D v3",
        "contentType": "Phaser v3 Animations"
    }
}